all_twitter_scraper/__init__.py
all_twitter_scraper/scraper.py
all_twitter_scraper/modules/Criteria.py
all_twitter_scraper/modules/Tweet.py
all_twitter_scraper/modules/Twitter_Scraper.py
all_twitter_scraper/modules/__init__.py
all_twitter_scraper/modules/constants.py
all_twitter_scraper/modules/helpers.py
all_twitter_scraper-0.0.4.dist-info/LICENSE
all_twitter_scraper-0.0.4.dist-info/METADATA
all_twitter_scraper-0.0.4.dist-info/WHEEL
all_twitter_scraper-0.0.4.dist-info/top_level.txt
all_twitter_scraper-0.0.4.dist-info/RECORD
