Metadata-Version: 2.1
Name: all-twitter-scraper
Version: 0.0.4
Summary: Get all tweets filtered by the parameters that are in twitter advanced search.
Home-page: https://github.com/samirian/all_twitter_scraper
Author: Abdallah Samir
Author-email: eng.abdallahsamir@gmail.com
License: MIT
Keywords: twitter tweets scraper
Platform: UNKNOWN
Requires-Python: >=3.4
Requires-Dist: lxml (>=4.4.0)
Requires-Dist: requests (>=2.21.0)
